ni_cts3/CardEmu.py
ni_cts3/CardEmuSeq.py
ni_cts3/CardHlSim.py
ni_cts3/Daq.py
ni_cts3/MPException.py
ni_cts3/MPStatus.py
ni_cts3/Measurement.py
ni_cts3/Nfc.py
ni_cts3/TermEmuSeq.py
ni_cts3/Wlc.py
ni_cts3/__init__.py
ni_cts3/py.typed
ni_cts3/.lib/Arm/libMPuLib.so
ni_cts3/.lib/Linux/x64/libMPuLib.so
ni_cts3/.lib/Linux/x86/libMPuLib.so
ni_cts3/.lib/Windows/MPuLib-win32.dll
ni_cts3/.lib/Windows/MPuLib-win64.dll
ni_cts3-25.0.1.dist-info/licenses/LICENSE
ni_cts3-25.0.1.dist-info/METADATA
ni_cts3-25.0.1.dist-info/WHEEL
ni_cts3-25.0.1.dist-info/top_level.txt
ni_cts3-25.0.1.dist-info/RECORD
